magicpy/__init__.py
magicpy/devices.py
magicpy/magicpy.py
magicpy/stimulator.py
magicpy/utils.py
magicpy-0.1.6.dist-info/LICENSE
magicpy-0.1.6.dist-info/METADATA
magicpy-0.1.6.dist-info/WHEEL
magicpy-0.1.6.dist-info/top_level.txt
magicpy-0.1.6.dist-info/RECORD
