Metadata-Version: 2.1
Name: magicpy
Version: 0.1.6
Summary: Toolbox to control MagVenture TMS stimulators
Home-page: UNKNOWN
Author: Ole Numssen
Author-email: numssen@posteo.de
License: UNKNOWN
Project-URL: Home, https://gitlab.gwdg.de/tms-localization/utils/magicpy
Project-URL: Docs, https://magicpy.readthedocs.io/
Project-URL: Twitter, https://twitter.com/num_ole
Project-URL: Download, https://pypi.org/project/magigpy/
Platform: UNKNOWN
Classifier: Development Status :: 3 - Alpha
Classifier: Intended Audience :: Science/Research
Classifier: Topic :: Scientific/Engineering
Classifier: Topic :: Software Development :: Build Tools
Classifier: Programming Language :: Python :: 3
Classifier: Programming Language :: Python :: 3.6
Classifier: Programming Language :: Python :: 3.7
Classifier: Programming Language :: Python :: 3.8
Classifier: Programming Language :: Python :: 3.9
License-File: LICENSE
Requires-Dist: pyserial >=3.5
Requires-Dist: numpy >=1.20.0
Requires-Dist: pyparallel
